ipydrop/__init__.py
ipydrop/static/widget.css
ipydrop/static/widget.js
ipydrop-0.0.1.dist-info/METADATA
ipydrop-0.0.1.dist-info/WHEEL
ipydrop-0.0.1.dist-info/licenses/LICENSE
ipydrop-0.0.1.dist-info/RECORD
