Metadata-Version: 2.3
Name: ipydrop
Version: 0.0.1
License-File: LICENSE
Requires-Dist: anywidget
Provides-Extra: dev
Requires-Dist: jupyterlab; extra == 'dev'
Requires-Dist: watchfiles; extra == 'dev'
